sixpi_example/__init__.py
sixpi_example/lib.py
example_pkg_sixpi-0.0.2.dist-info/LICENSE
example_pkg_sixpi-0.0.2.dist-info/METADATA
example_pkg_sixpi-0.0.2.dist-info/WHEEL
example_pkg_sixpi-0.0.2.dist-info/top_level.txt
example_pkg_sixpi-0.0.2.dist-info/RECORD
