Metadata-Version: 2.1
Name: example-pkg-sixpi
Version: 0.0.2
Summary: Example package
Home-page: https://bitbucket.org/sixpi/pypi-test
Author: Bing Xia
Author-email: bing@outlook.com
License: UNKNOWN
Platform: UNKNOWN
Classifier: Programming Language :: Python :: 3
Classifier: License :: OSI Approved :: MIT License
